{
	"configurations" : 
	[
		{
			"directories" : 
			[
				{
					"build" : ".",
					"childIndexes" : 
					[
						1,
						2
					],
					"hasInstallRule" : true,
					"jsonFile" : "directory-.-Debug-4b4af43c1f1fd471ae3d.json",
					"minimumCMakeVersion" : 
					{
						"string" : "3.14"
					},
					"projectIndex" : 0,
					"source" : "."
				},
				{
					"build" : "flutter",
					"jsonFile" : "directory-flutter-Debug-79e0260f2327d8493c28.json",
					"minimumCMakeVersion" : 
					{
						"string" : "3.14"
					},
					"parentIndex" : 0,
					"projectIndex" : 0,
					"source" : "flutter",
					"targetIndexes" : 
					[
						1,
						2,
						3
					]
				},
				{
					"build" : "runner",
					"jsonFile" : "directory-runner-Debug-86f38b7dcb6f33eb04e4.json",
					"minimumCMakeVersion" : 
					{
						"string" : "3.14"
					},
					"parentIndex" : 0,
					"projectIndex" : 1,
					"source" : "runner",
					"targetIndexes" : 
					[
						0
					]
				}
			],
			"name" : "Debug",
			"projects" : 
			[
				{
					"childIndexes" : 
					[
						1
					],
					"directoryIndexes" : 
					[
						0,
						1
					],
					"name" : "flutter_application_1",
					"targetIndexes" : 
					[
						1,
						2,
						3
					]
				},
				{
					"directoryIndexes" : 
					[
						2
					],
					"name" : "runner",
					"parentIndex" : 0,
					"targetIndexes" : 
					[
						0
					]
				}
			],
			"targets" : 
			[
				{
					"directoryIndex" : 2,
					"id" : "flutter_application_1::@056c4f61b0156d1d9b06",
					"jsonFile" : "target-flutter_application_1-Debug-17037cc48f42d79473c6.json",
					"name" : "flutter_application_1",
					"projectIndex" : 1
				},
				{
					"directoryIndex" : 1,
					"id" : "flutter_assemble::@2bb09fbb03a373b2cb34",
					"jsonFile" : "target-flutter_assemble-Debug-7fd3b1731921c52b9299.json",
					"name" : "flutter_assemble",
					"projectIndex" : 0
				},
				{
					"directoryIndex" : 1,
					"id" : "flutter_wrapper_app::@2bb09fbb03a373b2cb34",
					"jsonFile" : "target-flutter_wrapper_app-Debug-575597721901d4423e4b.json",
					"name" : "flutter_wrapper_app",
					"projectIndex" : 0
				},
				{
					"directoryIndex" : 1,
					"id" : "flutter_wrapper_plugin::@2bb09fbb03a373b2cb34",
					"jsonFile" : "target-flutter_wrapper_plugin-Debug-d99b6252a98e228b75a0.json",
					"name" : "flutter_wrapper_plugin",
					"projectIndex" : 0
				}
			]
		}
	],
	"kind" : "codemodel",
	"paths" : 
	{
		"build" : "C:/Users/Zubai/Desktop/Flutter/flutter_application_1/windows/out/build/x64-Debug",
		"source" : "C:/Users/Zubai/Desktop/Flutter/flutter_application_1/windows"
	},
	"version" : 
	{
		"major" : 2,
		"minor" : 3
	}
}
